input_generator/input_gen.vhd
library ieee;
use ieee.std_logic_1164.all;
use ieee.numeric_std.all;

library std;
use std.textio.all;


entity input_gen is
   port(
      clk: in std_logic;
      rst: in std_logic;
      sel: in std_logic_vector(1 downto 0);
      values_gen: out std_logic_vector(3 downto 0) 
   );
end;

architecture input_gen_arch of input_gen is
   constant LENGTH: positive := 1024;
   constant N: positive := 4;

   type rom is array(0 to LENGTH - 1) of std_logic_vector(3 downto 0);

   impure function init_rom_from_file(file_name: string) return rom is
      file input_file: text open read_mode is file_name;
      variable input_line: line;
      variable rom_values: rom;
   begin
      for i in rom'range loop
         readline(input_file, input_line);
         read(input_line, rom_values(i));
      end loop;
      return rom_values;
   end function;

   constant path_random: string := "/home/gianfranco/Documents/CESE/Circuitos Logicos Programables/Repositorio/CESE_Circuitos_Logicos_Programables/signals/input_random.data";
   constant path_tone: string := "/home/gianfranco/Documents/CESE/Circuitos Logicos Programables/Repositorio/CESE_Circuitos_Logicos_Programables/signals/input_tone.data";
   constant path_square: string := "/home/gianfranco/Documents/CESE/Circuitos Logicos Programables/Repositorio/CESE_Circuitos_Logicos_Programables/signals/input_square.data";

   constant values_random: rom :=  init_rom_from_file(path_random);
   constant values_tone: rom :=  init_rom_from_file(path_tone);
   constant values_square: rom :=  init_rom_from_file(path_square);

   signal counter: integer range 0 to 2**N - 1;
   signal pointer: integer range 0 to LENGTH - 1;
begin

   process (clk)
   begin
      if rising_edge(clk) then
         if rst then
            counter <= 0;
         elsif counter = 2**N - 1 then
            counter <= 0;
         else 
            counter <= counter + 1;
         end if;
      end if;
   end process;

   process (clk)
   begin
      if rising_edge(clk) then
         if rst then
            pointer <= 0;
         elsif counter = 2**N - 1 then
            if pointer = LENGTH - 1 then
               pointer <= 0;
            else 
               pointer <= pointer + 1;
            end if;
         end if;
      end if;
   end process;

   process (clk)
   begin
      if rising_edge(clk) then
         if rst then
            values_gen <= (others => '0');      
         else
            case sel is
               when "00" =>
                  values_gen <= values_random(pointer);    
               when "01" =>
                  values_gen <= values_tone(pointer);  
               when "10" =>
                  values_gen <= values_square(pointer);  
               when others =>
                  values_gen <= (others => '0');
               end case;
         end if;
      end if;
   end process;
   
end;

input_generator/input_gen_tb.vhd
library ieee;
use ieee.std_logic_1164.all;
use ieee.numeric_std.all;


entity input_gen_tb is
end;

architecture input_gen_tb_arch of input_gen_tb is
   procedure waitn_re(signal clk: std_logic; constant n: positive) is
      begin
         for i in 1 to n loop
            wait until rising_edge(clk);
      end loop;
   end procedure;

   component input_gen is
      port(
         clk: in std_logic;
         rst: in std_logic;
         sel: in std_logic_vector(1 downto 0);
         values_gen: out std_logic_vector(3 downto 0)
      );
   end component;

   constant RANDON_SIGNAL: std_logic_vector(1 downto 0) := "00";
   constant TONE_SIGNAL: std_logic_vector(1 downto 0) := "01";
   constant SQUARE_SIGNAL: std_logic_vector(1 downto 0) := "10";

   signal clk_tb: std_logic;
   signal rst_tb: std_logic;
   signal values_gen_tb: std_logic_vector(3 downto 0);
begin

   input_gen_inst: input_gen port map(
      clk => clk_tb,
      rst => rst_tb,
      sel => TONE_SIGNAL,
      values_gen => values_gen_tb
   );

   reset: process
   begin
      rst_tb <= '1';
      waitn_re(clk_tb, 2);
      rst_tb <= '0';
      wait;
   end process;

   clock: process
   begin
      clk_tb <= '0';
      wait for 1 ns;
      clk_tb <= '1';
      wait for 1 ns;
   end process;

end;

input_generator/input_gen_tb.vcd
$date
  Mon Oct 10 08:44:53 2022
$end
$version
  GHDL v0
$end
$timescale
  1 fs
$end
$scope module standard $end
$upscope $end
$scope module textio $end
$upscope $end
$scope module std_logic_1164 $end
$upscope $end
$scope module numeric_std $end
$upscope $end
$scope module input_gen_tb $end
$var reg 1 ! clk_tb $end
$var reg 1 " rst_tb $end
$var reg 4 # values_gen_tb[3:0] $end
$scope module input_gen_inst $end
$var reg 1 $ clk $end
$var reg 1 % rst $end
$var reg 2 & sel[1:0] $end
$var reg 4 ' values_gen[3:0] $end
$var integer 32 ( counter $end
$var integer 32 ) pointer $end
$upscope $end
$upscope $end
$enddefinitions $end
#0
0!
1"
bUUUU #
0$
1%
b01 &
bUUUU '
b0 (
b0 )
#1000000
1!
b0000 #
1$
b0000 '
#2000000
0!
0$
#3000000
1!
0"
1$
0%
#4000000
0!
0$
#5000000
1!
1$
b1 (
#6000000
0!
0$
#7000000
1!
1$
b10 (
#8000000
0!
0$
#9000000
1!
1$
b11 (
#10000000
0!
0$
#11000000
1!
1$
b100 (
#12000000
0!
0$
#13000000
1!
1$
b101 (
#14000000
0!
0$
#15000000
1!
1$
b110 (
#16000000
0!
0$
#17000000
1!
1$
b111 (
#18000000
0!
0$
#19000000
1!
1$
b1000 (
#20000000
0!
0$
#21000000
1!
1$
b1001 (
#22000000
0!
0$
#23000000
1!
1$
b1010 (
#24000000
0!
0$
#25000000
1!
1$
b1011 (
#26000000
0!
0$
#27000000
1!
1$
b1100 (
#28000000
0!
0$
#29000000
1!
1$
b1101 (
#30000000
0!
0$
#31000000
1!
1$
b1110 (
#32000000
0!
0$
#33000000
1!
1$
b1111 (
#34000000
0!
0$
#35000000
1!
1$
b0 (
b1 )
#36000000
0!
0$
#37000000
1!
b0010 #
1$
b0010 '
b1 (
#38000000
0!
0$
#39000000
1!
1$
b10 (
#40000000
0!
0$
#41000000
1!
1$
b11 (
#42000000
0!
0$
#43000000
1!
1$
b100 (
#44000000
0!
0$
#45000000
1!
1$
b101 (
#46000000
0!
0$
#47000000
1!
1$
b110 (
#48000000
0!
0$
#49000000
1!
1$
b111 (
#50000000
0!
0$
#51000000
1!
1$
b1000 (
#52000000
0!
0$
#53000000
1!
1$
b1001 (
#54000000
0!
0$
#55000000
1!
1$
b1010 (
#56000000
0!
0$
#57000000
1!
1$
b1011 (
#58000000
0!
0$
#59000000
1!
1$
b1100 (
#60000000
0!
0$
#61000000
1!
1$
b1101 (
#62000000
0!
0$
#63000000
1!
1$
b1110 (
#64000000
0!
0$
#65000000
1!
1$
b1111 (
#66000000
0!
0$
#67000000
1!
1$
b0 (
b10 )
#68000000
0!
0$
#69000000
1!
b0100 #
1$
b0100 '
b1 (
#70000000
0!
0$
#71000000
1!
1$
b10 (
#72000000
0!
0$
#73000000
1!
1$
b11 (
#74000000
0!
0$
#75000000
1!
1$
b100 (
#76000000
0!
0$
#77000000
1!
1$
b101 (
#78000000
0!
0$
#79000000
1!
1$
b110 (
#80000000
0!
0$
#81000000
1!
1$
b111 (
#82000000
0!
0$
#83000000
1!
1$
b1000 (
#84000000
0!
0$
#85000000
1!
1$
b1001 (
#86000000
0!
0$
#87000000
1!
1$
b1010 (
#88000000
0!
0$
#89000000
1!
1$
b1011 (
#90000000
0!
0$
#91000000
1!
1$
b1100 (
#92000000
0!
0$
#93000000
1!
1$
b1101 (
#94000000
0!
0$
#95000000
1!
1$
b1110 (
#96000000
0!
0$
#97000000
1!
1$
b1111 (
#98000000
0!
0$
#99000000
1!
1$
b0 (
b11 )
#100000000
0!
0$
#101000000
1!
b0101 #
1$
b0101 '
b1 (
#102000000
0!
0$
#103000000
1!
1$
b10 (
#104000000
0!
0$
#105000000
1!
1$
b11 (
#106000000
0!
0$
#107000000
1!
1$
b100 (
#108000000
0!
0$
#109000000
1!
1$
b101 (
#110000000
0!
0$
#111000000
1!
1$
b110 (
#112000000
0!
0$
#113000000
1!
1$
b111 (
#114000000
0!
0$
#115000000
1!
1$
b1000 (
#116000000
0!
0$
#117000000
1!
1$
b1001 (
#118000000
0!
0$
#119000000
1!
1$
b1010 (
#120000000
0!
0$
#121000000
1!
1$
b1011 (
#122000000
0!
0$
#123000000
1!
1$
b1100 (
#124000000
0!
0$
#125000000
1!
1$
b1101 (
#126000000
0!
0$
#127000000
1!
1$
b1110 (
#128000000
0!
0$
#129000000
1!
1$
b1111 (
#130000000
0!
0$
#131000000
1!
1$
b0 (
b100 )
#132000000
0!
0$
#133000000
1!
b0110 #
1$
b0110 '
b1 (
#134000000
0!
0$
#135000000
1!
1$
b10 (
#136000000
0!
0$
#137000000
1!
1$
b11 (
#138000000
0!
0$
#139000000
1!
1$
b100 (
#140000000
0!
0$
#141000000
1!
1$
b101 (
#142000000
0!
0$
#143000000
1!
1$
b110 (
#144000000
0!
0$
#145000000
1!
1$
b111 (
#146000000
0!
0$
#147000000
1!
1$
b1000 (
#148000000
0!
0$
#149000000
1!
1$
b1001 (
#150000000
0!
0$
#151000000
1!
1$
b1010 (
#152000000
0!
0$
#153000000
1!
1$
b1011 (
#154000000
0!
0$
#155000000
1!
1$
b1100 (
#156000000
0!
0$
#157000000
1!
1$
b1101 (
#158000000
0!
0$
#159000000
1!
1$
b1110 (
#160000000
0!
0$
#161000000
1!
1$
b1111 (
#162000000
0!
0$
#163000000
1!
1$
b0 (
b101 )
#164000000
0!
0$
#165000000
1!
1$
b1 (
#166000000
0!
0$
#167000000
1!
1$
b10 (
#168000000
0!
0$
#169000000
1!
1$
b11 (
#170000000
0!
0$
#171000000
1!
1$
b100 (
#172000000
0!
0$
#173000000
1!
1$
b101 (
#174000000
0!
0$
#175000000
1!
1$
b110 (
#176000000
0!
0$
#177000000
1!
1$
b111 (
#178000000
0!
0$
#179000000
1!
1$
b1000 (
#180000000
0!
0$
#181000000
1!
1$
b1001 (
#182000000
0!
0$
#183000000
1!
1$
b1010 (
#184000000
0!
0$
#185000000
1!
1$
b1011 (
#186000000
0!
0$
#187000000
1!
1$
b1100 (
#188000000
0!
0$
#189000000
1!
1$
b1101 (
#190000000
0!
0$
#191000000
1!
1$
b1110 (
#192000000
0!
0$
#193000000
1!
1$
b1111 (
#194000000
0!
0$
#195000000
1!
1$
b0 (
b110 )
#196000000
0!
0$
#197000000
1!
1$
b1 (
#198000000
0!
0$
#199000000
1!
1$
b10 (
#200000000
0!
0$
#201000000
1!
1$
b11 (
#202000000
0!
0$
#203000000
1!
1$
b100 (
#204000000
0!
0$
#205000000
1!
1$
b101 (
#206000000
0!
0$
#207000000
1!
1$
b110 (
#208000000
0!
0$
#209000000
1!
1$
b111 (
#210000000
0!
0$
#211000000
1!
1$
b1000 (
#212000000
0!
0$
#213000000
1!
1$
b1001 (
#214000000
0!
0$
#215000000
1!
1$
b1010 (
#216000000
0!
0$
#217000000
1!
1$
b1011 (
#218000000
0!
0$
#219000000
1!
1$
b1100 (
#220000000
0!
0$
#221000000
1!
1$
b1101 (
#222000000
0!
0$
#223000000
1!
1$
b1110 (
#224000000
0!
0$
#225000000
1!
1$
b1111 (
#226000000
0!
0$
#227000000
1!
1$
b0 (
b111 )
#228000000
0!
0$
#229000000
1!
b0101 #
1$
b0101 '
b1 (
#230000000
0!
0$
#231000000
1!
1$
b10 (
#232000000
0!
0$
#233000000
1!
1$
b11 (
#234000000
0!
0$
#235000000
1!
1$
b100 (
#236000000
0!
0$
#237000000
1!
1$
b101 (
#238000000
0!
0$
#239000000
1!
1$
b110 (
#240000000
0!
0$
#241000000
1!
1$
b111 (
#242000000
0!
0$
#243000000
1!
1$
b1000 (
#244000000
0!
0$
#245000000
1!
1$
b1001 (
#246000000
0!
0$
#247000000
1!
1$
b1010 (
#248000000
0!
0$
#249000000
1!
1$
b1011 (
#250000000
0!
0$
#251000000
1!
1$
b1100 (
#252000000
0!
0$
#253000000
1!
1$
b1101 (
#254000000
0!
0$
#255000000
1!
1$
b1110 (
#256000000
0!
0$
#257000000
1!
1$
b1111 (
#258000000
0!
0$
#259000000
1!
1$
b0 (
b1000 )
#260000000
0!
0$
#261000000
1!
b0100 #
1$
b0100 '
b1 (
#262000000
0!
0$
#263000000
1!
1$
b10 (
#264000000
0!
0$
#265000000
1!
1$
b11 (
#266000000
0!
0$
#267000000
1!
1$
b100 (
#268000000
0!
0$
#269000000
1!
1$
b101 (
#270000000
0!
0$
#271000000
1!
1$
b110 (
#272000000
0!
0$
#273000000
1!
1$
b111 (
#274000000
0!
0$
#275000000
1!
1$
b1000 (
#276000000
0!
0$
#277000000
1!
1$
b1001 (
#278000000
0!
0$
#279000000
1!
1$
b1010 (
#280000000
0!
0$
#281000000
1!
1$
b1011 (
#282000000
0!
0$
#283000000
1!
1$
b1100 (
#284000000
0!
0$
#285000000
1!
1$
b1101 (
#286000000
0!
0$
#287000000
1!
1$
b1110 (
#288000000
0!
0$
#289000000
1!
1$
b1111 (
#290000000
0!
0$
#291000000
1!
1$
b0 (
b1001 )
#292000000
0!
0$
#293000000
1!
b0010 #
1$
b0010 '
b1 (
#294000000
0!
0$
#295000000
1!
1$
b10 (
#296000000
0!
0$
#297000000
1!
1$
b11 (
#298000000
0!
0$
#299000000
1!
1$
b100 (
#300000000
0!
0$
#301000000
1!
1$
b101 (
#302000000
0!
0$
#303000000
1!
1$
b110 (
#304000000
0!
0$
#305000000
1!
1$
b111 (
#306000000
0!
0$
#307000000
1!
1$
b1000 (
#308000000
0!
0$
#309000000
1!
1$
b1001 (
#310000000
0!
0$
#311000000
1!
1$
b1010 (
#312000000
0!
0$
#313000000
1!
1$
b1011 (
#314000000
0!
0$
#315000000
1!
1$
b1100 (
#316000000
0!
0$
#317000000
1!
1$
b1101 (
#318000000
0!
0$
#319000000
1!
1$
b1110 (
#320000000
0!
0$
#321000000
1!
1$
b1111 (
#322000000
0!
0$
#323000000
1!
1$
b0 (
b1010 )
#324000000
0!
0$
#325000000
1!
b0000 #
1$
b0000 '
b1 (
#326000000
0!
0$
#327000000
1!
1$
b10 (
#328000000
0!
0$
#329000000
1!
1$
b11 (
#330000000
0!
0$
#331000000
1!
1$
b100 (
#332000000
0!
0$
#333000000
1!
1$
b101 (
#334000000
0!
0$
#335000000
1!
1$
b110 (
#336000000
0!
0$
#337000000
1!
1$
b111 (
#338000000
0!
0$
#339000000
1!
1$
b1000 (
#340000000
0!
0$
#341000000
1!
1$
b1001 (
#342000000
0!
0$
#343000000
1!
1$
b1010 (
#344000000
0!
0$
#345000000
1!
1$
b1011 (
#346000000
0!
0$
#347000000
1!
1$
b1100 (
#348000000
0!
0$
#349000000
1!
1$
b1101 (
#350000000
0!
0$
#351000000
1!
1$
b1110 (
#352000000
0!
0$
#353000000
1!
1$
b1111 (
#354000000
0!
0$
#355000000
1!
1$
b0 (
b1011 )
#356000000
0!
0$
#357000000
1!
b1111 #
1$
b1111 '
b1 (
#358000000
0!
0$
#359000000
1!
1$
b10 (
#360000000
0!
0$
#361000000
1!
1$
b11 (
#362000000
0!
0$
#363000000
1!
1$
b100 (
#364000000
0!
0$
#365000000
1!
1$
b101 (
#366000000
0!
0$
#367000000
1!
1$
b110 (
#368000000
0!
0$
#369000000
1!
1$
b111 (
#370000000
0!
0$
#371000000
1!
1$
b1000 (
#372000000
0!
0$
#373000000
1!
1$
b1001 (
#374000000
0!
0$
#375000000
1!
1$
b1010 (
#376000000
0!
0$
#377000000
1!
1$
b1011 (
#378000000
0!
0$
#379000000
1!
1$
b1100 (
#380000000
0!
0$
#381000000
1!
1$
b1101 (
#382000000
0!
0$
#383000000
1!
1$
b1110 (
#384000000
0!
0$
#385000000
1!
1$
b1111 (
#386000000
0!
0$
#387000000
1!
1$
b0 (
b1100 )
#388000000
0!
0$
#389000000
1!
b1101 #
1$
b1101 '
b1 (
#390000000
0!
0$
#391000000
1!
1$
b10 (
#392000000
0!
0$
#393000000
1!
1$
b11 (
#394000000
0!
0$
#395000000
1!
1$
b100 (
#396000000
0!
0$
#397000000
1!
1$
b101 (
#398000000
0!
0$
#399000000
1!
1$
b110 (
#400000000
0!
0$
#401000000
1!
1$
b111 (
#402000000
0!
0$
#403000000
1!
1$
b1000 (
#404000000
0!
0$
#405000000
1!
1$
b1001 (
#406000000
0!
0$
#407000000
1!
1$
b1010 (
#408000000
0!
0$
#409000000
1!
1$
b1011 (
#410000000
0!
0$
#411000000
1!
1$
b1100 (
#412000000
0!
0$
#413000000
1!
1$
b1101 (
#414000000
0!
0$
#415000000
1!
1$
b1110 (
#416000000
0!
0$
#417000000
1!
1$
b1111 (
#418000000
0!
0$
#419000000
1!
1$
b0 (
b1101 )
#420000000
0!
0$
#421000000
1!
b1011 #
1$
b1011 '
b1 (
#422000000
0!
0$
#423000000
1!
1$
b10 (
#424000000
0!
0$
#425000000
1!
1$
b11 (
#426000000
0!
0$
#427000000
1!
1$
b100 (
#428000000
0!
0$
#429000000
1!
1$
b101 (
#430000000
0!
0$
#431000000
1!
1$
b110 (
#432000000
0!
0$
#433000000
1!
1$
b111 (
#434000000
0!
0$
#435000000
1!
1$
b1000 (
#436000000
0!
0$
#437000000
1!
1$
b1001 (
#438000000
0!
0$
#439000000
1!
1$
b1010 (
#440000000
0!
0$
#441000000
1!
1$
b1011 (
#442000000
0!
0$
#443000000
1!
1$
b1100 (
#444000000
0!
0$
#445000000
1!
1$
b1101 (
#446000000
0!
0$
#447000000
1!
1$
b1110 (
#448000000
0!
0$
#449000000
1!
1$
b1111 (
#450000000
0!
0$
#451000000
1!
1$
b0 (
b1110 )
#452000000
0!
0$
#453000000
1!
b1010 #
1$
b1010 '
b1 (
#454000000
0!
0$
#455000000
1!
1$
b10 (
#456000000
0!
0$
#457000000
1!
1$
b11 (
#458000000
0!
0$
#459000000
1!
1$
b100 (
#460000000
0!
0$
#461000000
1!
1$
b101 (
#462000000
0!
0$
#463000000
1!
1$
b110 (
#464000000
0!
0$
#465000000
1!
1$
b111 (
#466000000
0!
0$
#467000000
1!
1$
b1000 (
#468000000
0!
0$
#469000000
1!
1$
b1001 (
#470000000
0!
0$
#471000000
1!
1$
b1010 (
#472000000
0!
0$
#473000000
1!
1$
b1011 (
#474000000
0!
0$
#475000000
1!
1$
b1100 (
#476000000
0!
0$
#477000000
1!
1$
b1101 (
#478000000
0!
0$
#479000000
1!
1$
b1110 (
#480000000
0!
0$
#481000000
1!
1$
b1111 (
#482000000
0!
0$
#483000000
1!
1$
b0 (
b1111 )
#484000000
0!
0$
#485000000
1!
1$
b1 (
#486000000
0!
0$
#487000000
1!
1$
b10 (
#488000000
0!
0$
#489000000
1!
1$
b11 (
#490000000
0!
0$
#491000000
1!
1$
b100 (
#492000000
0!
0$
#493000000
1!
1$
b101 (
#494000000
0!
0$
#495000000
1!
1$
b110 (
#496000000
0!
0$
#497000000
1!
1$
b111 (
#498000000
0!
0$
#499000000
1!
1$
b1000 (
#500000000
0!
0$
#501000000
1!
1$
b1001 (
#502000000
0!
0$
#503000000
1!
1$
b1010 (
#504000000
0!
0$
#505000000
1!
1$
b1011 (
#506000000
0!
0$
#507000000
1!
1$
b1100 (
#508000000
0!
0$
#509000000
1!
1$
b1101 (
#510000000
0!
0$
#511000000
1!
1$
b1110 (
#512000000
0!
0$
#513000000
1!
1$
b1111 (
#514000000
0!
0$
#515000000
1!
1$
b0 (
b10000 )
#516000000
0!
0$
#517000000
1!
1$
b1 (
#518000000
0!
0$
#519000000
1!
1$
b10 (
#520000000
0!
0$
#521000000
1!
1$
b11 (
#522000000
0!
0$
#523000000
1!
1$
b100 (
#524000000
0!
0$
#525000000
1!
1$
b101 (
#526000000
0!
0$
#527000000
1!
1$
b110 (
#528000000
0!
0$
#529000000
1!
1$
b111 (
#530000000
0!
0$
#531000000
1!
1$
b1000 (
#532000000
0!
0$
#533000000
1!
1$
b1001 (
#534000000
0!
0$
#535000000
1!
1$
b1010 (
#536000000
0!
0$
#537000000
1!
1$
b1011 (
#538000000
0!
0$
#539000000
1!
1$
b1100 (
#540000000
0!
0$
#541000000
1!
1$
b1101 (
#542000000
0!
0$
#543000000
1!
1$
b1110 (
#544000000
0!
0$
#545000000
1!
1$
b1111 (
#546000000
0!
0$
#547000000
1!
1$
b0 (
b10001 )
#548000000
0!
0$
#549000000
1!
1$
b1 (
#550000000
0!
0$
#551000000
1!
1$
b10 (
#552000000
0!
0$
#553000000
1!
1$
b11 (
#554000000
0!
0$
#555000000
1!
1$
b100 (
#556000000
0!
0$
#557000000
1!
1$
b101 (
#558000000
0!
0$
#559000000
1!
1$
b110 (
#560000000
0!
0$
#561000000
1!
1$
b111 (
#562000000
0!
0$
#563000000
1!
1$
b1000 (
#564000000
0!
0$
#565000000
1!
1$
b1001 (
#566000000
0!
0$
#567000000
1!
1$
b1010 (
#568000000
0!
0$
#569000000
1!
1$
b1011 (
#570000000
0!
0$
#571000000
1!
1$
b1100 (
#572000000
0!
0$
#573000000
1!
1$
b1101 (
#574000000
0!
0$
#575000000
1!
1$
b1110 (
#576000000
0!
0$
#577000000
1!
1$
b1111 (
#578000000
0!
0$
#579000000
1!
1$
b0 (
b10010 )
#580000000
0!
0$
#581000000
1!
b1100 #
1$
b1100 '
b1 (
#582000000
0!
0$
#583000000
1!
1$
b10 (
#584000000
0!
0$
#585000000
1!
1$
b11 (
#586000000
0!
0$
#587000000
1!
1$
b100 (
#588000000
0!
0$
#589000000
1!
1$
b101 (
#590000000
0!
0$
#591000000
1!
1$
b110 (
#592000000
0!
0$
#593000000
1!
1$
b111 (
#594000000
0!
0$
#595000000
1!
1$
b1000 (
#596000000
0!
0$
#597000000
1!
1$
b1001 (
#598000000
0!
0$
#599000000
1!
1$
b1010 (
#600000000
0!
0$
#601000000
1!
1$
b1011 (
#602000000
0!
0$
#603000000
1!
1$
b1100 (
#604000000
0!
0$
#605000000
1!
1$
b1101 (
#606000000
0!
0$
#607000000
1!
1$
b1110 (
#608000000
0!
0$
#609000000
1!
1$
b1111 (
#610000000
0!
0$
#611000000
1!
1$
b0 (
b10011 )
#612000000
0!
0$
#613000000
1!
b1101 #
1$
b1101 '
b1 (
#614000000
0!
0$
#615000000
1!
1$
b10 (
#616000000
0!
0$
#617000000
1!
1$
b11 (
#618000000
0!
0$
#619000000
1!
1$
b100 (
#620000000
0!
0$
#621000000
1!
1$
b101 (
#622000000
0!
0$
#623000000
1!
1$
b110 (
#624000000
0!
0$
#625000000
1!
1$
b111 (
#626000000
0!
0$
#627000000
1!
1$
b1000 (
#628000000
0!
0$
#629000000
1!
1$
b1001 (
#630000000
0!
0$
#631000000
1!
1$
b1010 (
#632000000
0!
0$
#633000000
1!
1$
b1011 (
#634000000
0!
0$
#635000000
1!
1$
b1100 (
#636000000
0!
0$
#637000000
1!
1$
b1101 (
#638000000
0!
0$
#639000000
1!
1$
b1110 (
#640000000
0!
0$
#641000000
1!
1$
b1111 (
#642000000
0!
0$
#643000000
1!
1$
b0 (
b10100 )
#644000000
0!
0$
#645000000
1!
b1111 #
1$
b1111 '
b1 (
#646000000
0!
0$
#647000000
1!
1$
b10 (
#648000000
0!
0$
#649000000
1!
1$
b11 (
#650000000
0!
0$
#651000000
1!
1$
b100 (
#652000000
0!
0$
#653000000
1!
1$
b101 (
#654000000
0!
0$
#655000000
1!
1$
b110 (
#656000000
0!
0$
#657000000
1!
1$
b111 (
#658000000
0!
0$
#659000000
1!
1$
b1000 (
#660000000
0!
0$
#661000000
1!
1$
b1001 (
#662000000
0!
0$
#663000000
1!
1$
b1010 (
#664000000
0!
0$
#665000000
1!
1$
b1011 (
#666000000
0!
0$
#667000000
1!
1$
b1100 (
#668000000
0!
0$
#669000000
1!
1$
b1101 (
#670000000
0!
0$
#671000000
1!
1$
b1110 (
#672000000
0!
0$
#673000000
1!
1$
b1111 (
#674000000
0!
0$
#675000000
1!
1$
b0 (
b10101 )
#676000000
0!
0$
#677000000
1!
b0001 #
1$
b0001 '
b1 (
#678000000
0!
0$
#679000000
1!
1$
b10 (
#680000000
0!
0$
#681000000
1!
1$
b11 (
#682000000
0!
0$
#683000000
1!
1$
b100 (
#684000000
0!
0$
#685000000
1!
1$
b101 (
#686000000
0!
0$
#687000000
1!
1$
b110 (
#688000000
0!
0$
#689000000
1!
1$
b111 (
#690000000
0!
0$
#691000000
1!
1$
b1000 (
#692000000
0!
0$
#693000000
1!
1$
b1001 (
#694000000
0!
0$
#695000000
1!
1$
b1010 (
#696000000
0!
0$
#697000000
1!
1$
b1011 (
#698000000
0!
0$
#699000000
1!
1$
b1100 (
#700000000
0!
0$
#701000000
1!
1$
b1101 (
#702000000
0!
0$
#703000000
1!
1$
b1110 (
#704000000
0!
0$
#705000000
1!
1$
b1111 (
#706000000
0!
0$
#707000000
1!
1$
b0 (
b10110 )
#708000000
0!
0$
#709000000
1!
b0011 #
1$
b0011 '
b1 (
#710000000
0!
0$
#711000000
1!
1$
b10 (
#712000000
0!
0$
#713000000
1!
1$
b11 (
#714000000
0!
0$
#715000000
1!
1$
b100 (
#716000000
0!
0$
#717000000
1!
1$
b101 (
#718000000
0!
0$
#719000000
1!
1$
b110 (
#720000000
0!
0$
#721000000
1!
1$
b111 (
#722000000
0!
0$
#723000000
1!
1$
b1000 (
#724000000
0!
0$
#725000000
1!
1$
b1001 (
#726000000
0!
0$
#727000000
1!
1$
b1010 (
#728000000
0!
0$
#729000000
1!
1$
b1011 (
#730000000
0!
0$
#731000000
1!
1$
b1100 (
#732000000
0!
0$
#733000000
1!
1$
b1101 (
#734000000
0!
0$
#735000000
1!
1$
b1110 (
#736000000
0!
0$
#737000000
1!
1$
b1111 (
#738000000
0!
0$
#739000000
1!
1$
b0 (
b10111 )
#740000000
0!
0$
#741000000
1!
b0100 #
1$
b0100 '
b1 (
#742000000
0!
0$
#743000000
1!
1$
b10 (
#744000000
0!
0$
#745000000
1!
1$
b11 (
#746000000
0!
0$
#747000000
1!
1$
b100 (
#748000000
0!
0$
#749000000
1!
1$
b101 (
#750000000
0!
0$
#751000000
1!
1$
b110 (
#752000000
0!
0$
#753000000
1!
1$
b111 (
#754000000
0!
0$
#755000000
1!
1$
b1000 (
#756000000
0!
0$
#757000000
1!
1$
b1001 (
#758000000
0!
0$
#759000000
1!
1$
b1010 (
#760000000
0!
0$
#761000000
1!
1$
b1011 (
#762000000
0!
0$
#763000000
1!
1$
b1100 (
#764000000
0!
0$
#765000000
1!
1$
b1101 (
#766000000
0!
0$
#767000000
1!
1$
b1110 (
#768000000
0!
0$
#769000000
1!
1$
b1111 (
#770000000
0!
0$
#771000000
1!
1$
b0 (
b11000 )
#772000000
0!
0$
#773000000
1!
b0110 #
1$
b0110 '
b1 (
#774000000
0!
0$
#775000000
1!
1$
b10 (
#776000000
0!
0$
#777000000
1!
1$
b11 (
#778000000
0!
0$
#779000000
1!
1$
b100 (
#780000000
0!
0$
#781000000
1!
1$
b101 (
#782000000
0!
0$
#783000000
1!
1$
b110 (
#784000000
0!
0$
#785000000
1!
1$
b111 (
#786000000
0!
0$
#787000000
1!
1$
b1000 (
#788000000
0!
0$
#789000000
1!
1$
b1001 (
#790000000
0!
0$
#791000000
1!
1$
b1010 (
#792000000
0!
0$
#793000000
1!
1$
b1011 (
#794000000
0!
0$
#795000000
1!
1$
b1100 (
#796000000
0!
0$
#797000000
1!
1$
b1101 (
#798000000
0!
0$
#799000000
1!
1$
b1110 (
#800000000
0!
0$
#801000000
1!
1$
b1111 (
#802000000
0!
0$
#803000000
1!
1$
b0 (
b11001 )
#804000000
0!
0$
#805000000
1!
1$
b1 (
#806000000
0!
0$
#807000000
1!
1$
b10 (
#808000000
0!
0$
#809000000
1!
1$
b11 (
#810000000
0!
0$
#811000000
1!
1$
b100 (
#812000000
0!
0$
#813000000
1!
1$
b101 (
#814000000
0!
0$
#815000000
1!
1$
b110 (
#816000000
0!
0$
#817000000
1!
1$
b111 (
#818000000
0!
0$
#819000000
1!
1$
b1000 (
#820000000
0!
0$
#821000000
1!
1$
b1001 (
#822000000
0!
0$
#823000000
1!
1$
b1010 (
#824000000
0!
0$
#825000000
1!
1$
b1011 (
#826000000
0!
0$
#827000000
1!
1$
b1100 (
#828000000
0!
0$
#829000000
1!
1$
b1101 (
#830000000
0!
0$
#831000000
1!
1$
b1110 (
#832000000
0!
0$
#833000000
1!
1$
b1111 (
#834000000
0!
0$
#835000000
1!
1$
b0 (
b11010 )
#836000000
0!
0$
#837000000
1!
1$
b1 (
#838000000
0!
0$
#839000000
1!
1$
b10 (
#840000000
0!
0$
#841000000
1!
1$
b11 (
#842000000
0!
0$
#843000000
1!
1$
b100 (
#844000000
0!
0$
#845000000
1!
1$
b101 (
#846000000
0!
0$
#847000000
1!
1$
b110 (
#848000000
0!
0$
#849000000
1!
1$
b111 (
#850000000
0!
0$
#851000000
1!
1$
b1000 (
#852000000
0!
0$
#853000000
1!
1$
b1001 (
#854000000
0!
0$
#855000000
1!
1$
b1010 (
#856000000
0!
0$
#857000000
1!
1$
b1011 (
#858000000
0!
0$
#859000000
1!
1$
b1100 (
#860000000
0!
0$
#861000000
1!
1$
b1101 (
#862000000
0!
0$
#863000000
1!
1$
b1110 (
#864000000
0!
0$
#865000000
1!
1$
b1111 (
#866000000
0!
0$
#867000000
1!
1$
b0 (
b11011 )
#868000000
0!
0$
#869000000
1!
1$
b1 (
#870000000
0!
0$
#871000000
1!
1$
b10 (
#872000000
0!
0$
#873000000
1!
1$
b11 (
#874000000
0!
0$
#875000000
1!
1$
b100 (
#876000000
0!
0$
#877000000
1!
1$
b101 (
#878000000
0!
0$
#879000000
1!
1$
b110 (
#880000000
0!
0$
#881000000
1!
1$
b111 (
#882000000
0!
0$
#883000000
1!
1$
b1000 (
#884000000
0!
0$
#885000000
1!
1$
b1001 (
#886000000
0!
0$
#887000000
1!
1$
b1010 (
#888000000
0!
0$
#889000000
1!
1$
b1011 (
#890000000
0!
0$
#891000000
1!
1$
b1100 (
#892000000
0!
0$
#893000000
1!
1$
b1101 (
#894000000
0!
0$
#895000000
1!
1$
b1110 (
#896000000
0!
0$
#897000000
1!
1$
b1111 (
#898000000
0!
0$
#899000000
1!
1$
b0 (
b11100 )
#900000000
0!
0$
#901000000
1!
b0101 #
1$
b0101 '
b1 (
#902000000
0!
0$
#903000000
1!
1$
b10 (
#904000000
0!
0$
#905000000
1!
1$
b11 (
#906000000
0!
0$
#907000000
1!
1$
b100 (
#908000000
0!
0$
